mantarray/__init__.py
mantarray-0.0.0.dist-info/METADATA
mantarray-0.0.0.dist-info/WHEEL
mantarray-0.0.0.dist-info/top_level.txt
mantarray-0.0.0.dist-info/RECORD
