Metadata-Version: 2.1
Name: mantarray
Version: 0.0.0
Summary: Coming soon
Author-email: Daniel Mesejo <mesejoleon@gmail.com>
